{
	"configurations" : 
	[
		{
			"directories" : 
			[
				{
					"build" : ".",
					"jsonFile" : "directory-.-Debug-f5ebdc15457944623624.json",
					"minimumCMakeVersion" : 
					{
						"string" : "3.10"
					},
					"projectIndex" : 0,
					"source" : ".",
					"targetIndexes" : 
					[
						0
					]
				}
			],
			"name" : "Debug",
			"projects" : 
			[
				{
					"directoryIndexes" : 
					[
						0
					],
					"name" : "pca_cache_proj",
					"targetIndexes" : 
					[
						0
					]
				}
			],
			"targets" : 
			[
				{
					"directoryIndex" : 0,
					"id" : "pca_cache_proj::@6890427a1f51a3e7e1df",
					"jsonFile" : "target-pca_cache_proj-Debug-50ca0764790370fa6daa.json",
					"name" : "pca_cache_proj",
					"projectIndex" : 0
				}
			]
		}
	],
	"kind" : "codemodel",
	"paths" : 
	{
		"build" : "/home/dmit/Desktop/vlados/Cache/pca_cache/build",
		"source" : "/home/dmit/Desktop/vlados/Cache/pca_cache"
	},
	"version" : 
	{
		"major" : 2,
		"minor" : 3
	}
}
